termalign/__init__.py
termalign/columns.py
termalign/core.py
termalign/formatter.py
termalign/multicolumn.py
termalign/table.py
termalign/utils.py
termalign-0.1.1.dist-info/licenses/LICENSE
termalign-0.1.1.dist-info/METADATA
termalign-0.1.1.dist-info/WHEEL
termalign-0.1.1.dist-info/top_level.txt
termalign-0.1.1.dist-info/RECORD
