Metadata-Version: 2.4
Name: termalign
Version: 0.1.1
Summary: Advanced text formatting and alignment for terminal output
Author-email: Croketillo <croketillo@gmail.com>
License-Expression: MIT
Project-URL: Homepage, https://github.com/croketillo/termalign
Classifier: Intended Audience :: Developers
Classifier: Topic :: Text Processing
Classifier: Topic :: Software Development :: Libraries
Classifier: Programming Language :: Python :: 3
Classifier: Programming Language :: Python :: 3.8
Classifier: Programming Language :: Python :: 3.9
Classifier: Programming Language :: Python :: 3.10
Classifier: Programming Language :: Python :: 3.11
Classifier: Programming Language :: Python :: 3.12
Classifier: Operating System :: OS Independent
Requires-Python: >=3.7
License-File: LICENSE
Dynamic: license-file
